{
    "cortex": {
        "pag": "aggregate001",
        "sync_rate": "200ms",
        "duration_threshold": "2s",
        "twin_configs": [
            {
                "db_config": {
                    "table": "ac",
                    "uri": "postgres://postgres:postgrespw@postgres:5432"
                },
                "vse_config": {
                    "hnsw_config": {
                        "full_scan_threshold": 10000,
                        "max_indexing_threads": 0,
                        "m": 16,
                        "ef_construct": 100
                    },
                    "wal_config": {
                        "wal_capacity_mb": 32,
                        "wal_segments_ahead": 0
                    },
                    "optimizer_config": {
                        "deleted_threshold": 0.2,
                        "vacuum_min_vector_number": 1000,
                        "default_segment_number": 0,
                        "max_segment_size": null,
                        "memmap_threshold": null,
                        "indexing_threshold": 2000,
                        "flush_interval_sec": 5,
                        "max_optimization_threads": 1
                    },
                    "shard_number": null,
                    "timeout": 10,
                    "vse_url": "qdrant://qdrant:6334",
                    "similarity_metric": "euclid",
                    "on_disk_payload": null
                },
                "log_config": {
                    "level": "error",
                    "log_file": "/tmp/ac.log"
                },
                "physical_twin_type": "actuator",
                "shape": 1,
                "display_name": "Air Conditioner",
                "module_id": "air_conditioner",
                "duration_threshold": "1s",
                "sync_rate": "1s",
                "sync_once": false,
                "broker_config": {
                    "url": "kafka:9093",
                    "sub_topic": "ac_sub",
                    "pub_topic": "ac_pub",
                    "group": "actuators",
                    "auto_offset_reset": "latest"
                },
                "ras_config": {
                    "upsert_from": "json",
                    "file_path": "/avenieca/ac_ras.json"
                },
                "in_twins": [],
                "out_twins": []
            },
            {
                "db_config": {
                    "table": "aqi",
                    "uri": "postgres://postgres:postgrespw@postgres:5432"
                },
                "vse_config": {
                    "hnsw_config": {
                        "full_scan_threshold": 10000,
                        "max_indexing_threads": 0,
                        "m": 16,
                        "ef_construct": 100
                    },
                    "wal_config": {
                        "wal_capacity_mb": 32,
                        "wal_segments_ahead": 0
                    },
                    "optimizer_config": {
                        "deleted_threshold": 0.2,
                        "vacuum_min_vector_number": 1000,
                        "default_segment_number": 0,
                        "max_segment_size": null,
                        "memmap_threshold": null,
                        "indexing_threshold": 2000,
                        "flush_interval_sec": 5,
                        "max_optimization_threads": 1
                    },
                    "shard_number": null,
                    "timeout": 10,
                    "vse_url": "qdrant://qdrant:6334",
                    "similarity_metric": "euclid",
                    "on_disk_payload": null
                },
                "log_config": {
                    "level": "error",
                    "log_file": "/tmp/aqi.log"
                },
                "physical_twin_type": "sensor",
                "shape": 1,
                "display_name": "Air Quality Index",
                "module_id": "air_quality_index",
                "duration_threshold": "1s",
                "sync_rate": "1s",
                "sync_once": false,
                "broker_config": {
                    "url": "kafka:9093",
                    "sub_topic": "aqi_sub",
                    "pub_topic": "",
                    "group": "sensors",
                    "auto_offset_reset": "latest"
                },
                "ras_config": {
                    "upsert_from": "json",
                    "file_path": "/avenieca/aqi_ras.json"
                },
                "in_twins": [],
                "out_twins": []
            },
            {
                "db_config": {
                    "table": "occupancy",
                    "uri": "postgres://postgres:postgrespw@postgres:5432"
                },
                "vse_config": {
                    "hnsw_config": {
                        "full_scan_threshold": 10000,
                        "max_indexing_threads": 0,
                        "m": 16,
                        "ef_construct": 100
                    },
                    "wal_config": {
                        "wal_capacity_mb": 32,
                        "wal_segments_ahead": 0
                    },
                    "optimizer_config": {
                        "deleted_threshold": 0.2,
                        "vacuum_min_vector_number": 1000,
                        "default_segment_number": 0,
                        "max_segment_size": null,
                        "memmap_threshold": null,
                        "indexing_threshold": 2000,
                        "flush_interval_sec": 5,
                        "max_optimization_threads": 1
                    },
                    "shard_number": null,
                    "timeout": 10,
                    "vse_url": "qdrant://qdrant:6334",
                    "similarity_metric": "euclid",
                    "on_disk_payload": null
                },
                "log_config": {
                    "level": "error",
                    "log_file": "/tmp/occupancy.log"
                },
                "physical_twin_type": "sensor",
                "shape": 1,
                "display_name": "Occupancy",
                "module_id": "occupancy",
                "duration_threshold": "1s",
                "sync_rate": "1s",
                "sync_once": false,
                "broker_config": {
                    "url": "kafka:9093",
                    "sub_topic": "occupancy_sub",
                    "pub_topic": "",
                    "group": "sensor",
                    "auto_offset_reset": "latest"
                },
                "ras_config": {
                    "upsert_from": "json",
                    "file_path": "/avenieca/occupancy_ras.json"
                },
                "in_twins": [],
                "out_twins": []
            },
            {
                "db_config": {
                    "table": "purifier",
                    "uri": "postgres://postgres:postgrespw@postgres:5432"
                },
                "vse_config": {
                    "hnsw_config": {
                        "full_scan_threshold": 10000,
                        "max_indexing_threads": 0,
                        "m": 16,
                        "ef_construct": 100
                    },
                    "wal_config": {
                        "wal_capacity_mb": 32,
                        "wal_segments_ahead": 0
                    },
                    "optimizer_config": {
                        "deleted_threshold": 0.2,
                        "vacuum_min_vector_number": 1000,
                        "default_segment_number": 0,
                        "max_segment_size": null,
                        "memmap_threshold": null,
                        "indexing_threshold": 2000,
                        "flush_interval_sec": 5,
                        "max_optimization_threads": 1
                    },
                    "shard_number": null,
                    "timeout": 10,
                    "vse_url": "qdrant://qdrant:6334",
                    "similarity_metric": "euclid",
                    "on_disk_payload": null
                },
                "log_config": {
                    "level": "error",
                    "log_file": "/tmp/purifier.log"
                },
                "physical_twin_type": "actuator",
                "shape": 1,
                "display_name": "Purifier",
                "module_id": "purifier",
                "duration_threshold": "1s",
                "sync_rate": "1s",
                "sync_once": false,
                "broker_config": {
                    "url": "kafka:9093",
                    "sub_topic": "purifier_sub",
                    "pub_topic": "purifier_pub",
                    "group": "actuator",
                    "auto_offset_reset": "latest"
                },
                "ras_config": {
                    "upsert_from": "json",
                    "file_path": "/avenieca/purifier_ras.json"
                },
                "in_twins": [],
                "out_twins": []
            },
            {
                "db_config": {
                    "table": "temperature",
                    "uri": "postgres://postgres:postgrespw@postgres:5432"
                },
                "vse_config": {
                    "hnsw_config": {
                        "full_scan_threshold": 10000,
                        "max_indexing_threads": 0,
                        "m": 16,
                        "ef_construct": 100
                    },
                    "wal_config": {
                        "wal_capacity_mb": 32,
                        "wal_segments_ahead": 0
                    },
                    "optimizer_config": {
                        "deleted_threshold": 0.2,
                        "vacuum_min_vector_number": 1000,
                        "default_segment_number": 0,
                        "max_segment_size": null,
                        "memmap_threshold": null,
                        "indexing_threshold": 2000,
                        "flush_interval_sec": 5,
                        "max_optimization_threads": 1
                    },
                    "shard_number": null,
                    "timeout": 10,
                    "vse_url": "qdrant://qdrant:6334",
                    "similarity_metric": "euclid",
                    "on_disk_payload": null
                },
                "log_config": {
                    "level": "error",
                    "log_file": "/tmp/temperature.log"
                },
                "physical_twin_type": "sensor",
                "shape": 1,
                "display_name": "Temperature (Celsius)",
                "module_id": "temperature",
                "duration_threshold": "1s",
                "sync_rate": "1s",
                "sync_once": false,
                "broker_config": {
                    "url": "kafka:9093",
                    "sub_topic": "temperature_sub",
                    "pub_topic": "",
                    "group": "sensor",
                    "auto_offset_reset": "latest"
                },
                "ras_config": {
                    "upsert_from": "json",
                    "file_path": "/avenieca/temperature_ras.json"
                },
                "in_twins": [],
                "out_twins": []
            },
            {
                "db_config": {
                    "table": "pag",
                    "uri": "postgres://postgres:postgrespw@postgres:5432"
                },
                "vse_config": {
                    "hnsw_config": {
                        "full_scan_threshold": 10000,
                        "max_indexing_threads": 0,
                        "m": 16,
                        "ef_construct": 100
                    },
                    "wal_config": {
                        "wal_capacity_mb": 32,
                        "wal_segments_ahead": 0
                    },
                    "optimizer_config": {
                        "deleted_threshold": 0.2,
                        "vacuum_min_vector_number": 1000,
                        "default_segment_number": 0,
                        "max_segment_size": null,
                        "memmap_threshold": null,
                        "indexing_threshold": 2000,
                        "flush_interval_sec": 5,
                        "max_optimization_threads": 1
                    },
                    "shard_number": null,
                    "timeout": 10,
                    "vse_url": "qdrant://qdrant:6334",
                    "similarity_metric": "euclid",
                    "on_disk_payload": null
                },
                "log_config": {
                    "level": "error",
                    "log_file": "/tmp/aggregate001.log"
                },
                "physical_twin_type": "",
                "shape": 5,
                "display_name": "PAG",
                "module_id": "aggregate001",
                "duration_threshold": "5s",
                "sync_rate": "1s",
                "sync_once": false,
                "broker_config": null,
                "ras_config": null,
                "in_twins": [
                    {
                        "db_config": {
                            "table": "ac",
                            "uri": "postgres://postgres:postgrespw@postgres:5432"
                        },
                        "vse_config": {
                            "hnsw_config": {
                                "full_scan_threshold": 10000,
                                "max_indexing_threads": 0,
                                "m": 16,
                                "ef_construct": 100
                            },
                            "wal_config": {
                                "wal_capacity_mb": 32,
                                "wal_segments_ahead": 0
                            },
                            "optimizer_config": {
                                "deleted_threshold": 0.2,
                                "vacuum_min_vector_number": 1000,
                                "default_segment_number": 0,
                                "max_segment_size": null,
                                "memmap_threshold": null,
                                "indexing_threshold": 2000,
                                "flush_interval_sec": 5,
                                "max_optimization_threads": 1
                            },
                            "shard_number": null,
                            "timeout": 10,
                            "vse_url": "qdrant://qdrant:6334",
                            "similarity_metric": "euclid",
                            "on_disk_payload": null
                        },
                        "log_config": {
                            "level": "error",
                            "log_file": "/tmp/ac.log"
                        },
                        "physical_twin_type": "actuator",
                        "shape": 1,
                        "display_name": "Air Conditioner",
                        "module_id": "air_conditioner",
                        "duration_threshold": "1s",
                        "sync_rate": "1s",
                        "sync_once": false,
                        "broker_config": {
                            "url": "kafka:9093",
                            "sub_topic": "ac_sub",
                            "pub_topic": "ac_pub",
                            "group": "actuators",
                            "auto_offset_reset": "latest"
                        },
                        "ras_config": {
                            "upsert_from": "json",
                            "file_path": "/avenieca/ac_ras.json"
                        },
                        "in_twins": [],
                        "out_twins": []
                    },
                    {
                        "db_config": {
                            "table": "aqi",
                            "uri": "postgres://postgres:postgrespw@postgres:5432"
                        },
                        "vse_config": {
                            "hnsw_config": {
                                "full_scan_threshold": 10000,
                                "max_indexing_threads": 0,
                                "m": 16,
                                "ef_construct": 100
                            },
                            "wal_config": {
                                "wal_capacity_mb": 32,
                                "wal_segments_ahead": 0
                            },
                            "optimizer_config": {
                                "deleted_threshold": 0.2,
                                "vacuum_min_vector_number": 1000,
                                "default_segment_number": 0,
                                "max_segment_size": null,
                                "memmap_threshold": null,
                                "indexing_threshold": 2000,
                                "flush_interval_sec": 5,
                                "max_optimization_threads": 1
                            },
                            "shard_number": null,
                            "timeout": 10,
                            "vse_url": "qdrant://qdrant:6334",
                            "similarity_metric": "euclid",
                            "on_disk_payload": null
                        },
                        "log_config": {
                            "level": "error",
                            "log_file": "/tmp/aqi.log"
                        },
                        "physical_twin_type": "sensor",
                        "shape": 1,
                        "display_name": "Air Quality Index",
                        "module_id": "air_quality_index",
                        "duration_threshold": "1s",
                        "sync_rate": "1s",
                        "sync_once": false,
                        "broker_config": {
                            "url": "kafka:9093",
                            "sub_topic": "aqi_sub",
                            "pub_topic": "",
                            "group": "sensors",
                            "auto_offset_reset": "latest"
                        },
                        "ras_config": {
                            "upsert_from": "json",
                            "file_path": "/avenieca/aqi_ras.json"
                        },
                        "in_twins": [],
                        "out_twins": []
                    },
                    {
                        "db_config": {
                            "table": "occupancy",
                            "uri": "postgres://postgres:postgrespw@postgres:5432"
                        },
                        "vse_config": {
                            "hnsw_config": {
                                "full_scan_threshold": 10000,
                                "max_indexing_threads": 0,
                                "m": 16,
                                "ef_construct": 100
                            },
                            "wal_config": {
                                "wal_capacity_mb": 32,
                                "wal_segments_ahead": 0
                            },
                            "optimizer_config": {
                                "deleted_threshold": 0.2,
                                "vacuum_min_vector_number": 1000,
                                "default_segment_number": 0,
                                "max_segment_size": null,
                                "memmap_threshold": null,
                                "indexing_threshold": 2000,
                                "flush_interval_sec": 5,
                                "max_optimization_threads": 1
                            },
                            "shard_number": null,
                            "timeout": 10,
                            "vse_url": "qdrant://qdrant:6334",
                            "similarity_metric": "euclid",
                            "on_disk_payload": null
                        },
                        "log_config": {
                            "level": "error",
                            "log_file": "/tmp/occupancy.log"
                        },
                        "physical_twin_type": "sensor",
                        "shape": 1,
                        "display_name": "Occupancy",
                        "module_id": "occupancy",
                        "duration_threshold": "1s",
                        "sync_rate": "1s",
                        "sync_once": false,
                        "broker_config": {
                            "url": "kafka:9093",
                            "sub_topic": "occupancy_sub",
                            "pub_topic": "",
                            "group": "sensor",
                            "auto_offset_reset": "latest"
                        },
                        "ras_config": {
                            "upsert_from": "json",
                            "file_path": "/avenieca/occupancy_ras.json"
                        },
                        "in_twins": [],
                        "out_twins": []
                    },
                    {
                        "db_config": {
                            "table": "purifier",
                            "uri": "postgres://postgres:postgrespw@postgres:5432"
                        },
                        "vse_config": {
                            "hnsw_config": {
                                "full_scan_threshold": 10000,
                                "max_indexing_threads": 0,
                                "m": 16,
                                "ef_construct": 100
                            },
                            "wal_config": {
                                "wal_capacity_mb": 32,
                                "wal_segments_ahead": 0
                            },
                            "optimizer_config": {
                                "deleted_threshold": 0.2,
                                "vacuum_min_vector_number": 1000,
                                "default_segment_number": 0,
                                "max_segment_size": null,
                                "memmap_threshold": null,
                                "indexing_threshold": 2000,
                                "flush_interval_sec": 5,
                                "max_optimization_threads": 1
                            },
                            "shard_number": null,
                            "timeout": 10,
                            "vse_url": "qdrant://qdrant:6334",
                            "similarity_metric": "euclid",
                            "on_disk_payload": null
                        },
                        "log_config": {
                            "level": "error",
                            "log_file": "/tmp/purifier.log"
                        },
                        "physical_twin_type": "actuator",
                        "shape": 1,
                        "display_name": "Purifier",
                        "module_id": "purifier",
                        "duration_threshold": "1s",
                        "sync_rate": "1s",
                        "sync_once": false,
                        "broker_config": {
                            "url": "kafka:9093",
                            "sub_topic": "purifier_sub",
                            "pub_topic": "purifier_pub",
                            "group": "actuator",
                            "auto_offset_reset": "latest"
                        },
                        "ras_config": {
                            "upsert_from": "json",
                            "file_path": "/avenieca/purifier_ras.json"
                        },
                        "in_twins": [],
                        "out_twins": []
                    },
                    {
                        "db_config": {
                            "table": "temperature",
                            "uri": "postgres://postgres:postgrespw@postgres:5432"
                        },
                        "vse_config": {
                            "hnsw_config": {
                                "full_scan_threshold": 10000,
                                "max_indexing_threads": 0,
                                "m": 16,
                                "ef_construct": 100
                            },
                            "wal_config": {
                                "wal_capacity_mb": 32,
                                "wal_segments_ahead": 0
                            },
                            "optimizer_config": {
                                "deleted_threshold": 0.2,
                                "vacuum_min_vector_number": 1000,
                                "default_segment_number": 0,
                                "max_segment_size": null,
                                "memmap_threshold": null,
                                "indexing_threshold": 2000,
                                "flush_interval_sec": 5,
                                "max_optimization_threads": 1
                            },
                            "shard_number": null,
                            "timeout": 10,
                            "vse_url": "qdrant://qdrant:6334",
                            "similarity_metric": "euclid",
                            "on_disk_payload": null
                        },
                        "log_config": {
                            "level": "error",
                            "log_file": "/tmp/temperature.log"
                        },
                        "physical_twin_type": "sensor",
                        "shape": 1,
                        "display_name": "Temperature (Celsius)",
                        "module_id": "temperature",
                        "duration_threshold": "1s",
                        "sync_rate": "1s",
                        "sync_once": false,
                        "broker_config": {
                            "url": "kafka:9093",
                            "sub_topic": "temperature_sub",
                            "pub_topic": "",
                            "group": "sensor",
                            "auto_offset_reset": "latest"
                        },
                        "ras_config": {
                            "upsert_from": "json",
                            "file_path": "/avenieca/temperature_ras.json"
                        },
                        "in_twins": [],
                        "out_twins": []
                    }
                ],
                "out_twins": []
            }
        ],
        "db_config": {
            "table": "core",
            "uri": "postgres://postgres:postgrespw@postgres:5432"
        },
        "log_config": {
            "level": "error",
            "log_file": "/tmp/avenieca_core_respond.log"
        },
        "name": "core",
        "recall": 20,
        "range": 20,
        "sync_once": false
    }
}